dexter_controller/__init__.py
dexter_controller/dexter_hand_controller.py
dexter_controller/finger.py
dexter_controller/loadcell_device.py
dexter_controller-0.1.2.dist-info/WHEEL
dexter_controller-0.1.2.dist-info/METADATA
dexter_controller-0.1.2.dist-info/RECORD
