Metadata-Version: 2.3
Name: dexter-controller
Version: 0.1.2
Summary: Dexter Controller for the HARP Load Cells
Author: Hardware and Software Platform, Champalimaud Foundation
Author-email: Hardware and Software Platform, Champalimaud Foundation <software@research.fchampalimaud.org>
Requires-Dist: harp-loadcells>=0.1.0a3
Requires-Python: >=3.10
Project-URL: Bug Tracker, https://github.com/fchampalimaud/dexter-controller/issues
Project-URL: Repository, https://github.com/fchampalimaud/dexter-controller/
